sos_api_1/__init__.py
sos_api_1/core.py
sos_api_1-0.1.0.dist-info/METADATA
sos_api_1-0.1.0.dist-info/WHEEL
sos_api_1-0.1.0.dist-info/RECORD
