Metadata-Version: 2.3
Name: sos_api_1
Version: 0.1.0
Summary: 
Author: Shaunak Deshpande
Author-email: shaunakd75@gmail.com
Requires-Python: >=3.12
Classifier: Programming Language :: Python :: 3
Classifier: Programming Language :: Python :: 3.12
Classifier: Programming Language :: Python :: 3.13
